LICENSE
MANIFEST.in
README.md
pyproject.toml
requirements.txt
setup.cfg
setup.py
tfclip/__init__.py
tfclip/abspos.py
tfclip/attnpool.py
tfclip/bpe_simple_vocab_16e6.txt.gz
tfclip/clstok.py
tfclip/constants.py
tfclip/evattn.py
tfclip/factory.py
tfclip/itsim.py
tfclip/lscale.py
tfclip/mapool.py
tfclip/model.py
tfclip/pretrain.py
tfclip/qgelu.py
tfclip/text.py
tfclip/tlcm.py
tfclip/tokenizer.py
tfclip/transform.py
tfclip/txtpool.py
tfclip/utils.py
tfclip/vision.py
tfclip.egg-info/PKG-INFO
tfclip.egg-info/SOURCES.txt
tfclip.egg-info/dependency_links.txt
tfclip.egg-info/requires.txt
tfclip.egg-info/top_level.txt
tfclip/configs/EVA01-g-14-plus.json
tfclip/configs/EVA01-g-14.json
tfclip/configs/EVA02-B-16.json
tfclip/configs/EVA02-E-14-plus.json
tfclip/configs/EVA02-E-14.json
tfclip/configs/EVA02-L-14-336.json
tfclip/configs/EVA02-L-14.json
tfclip/configs/ViT-B-16-Long-quickgelu.json
tfclip/configs/ViT-B-16-SigLIP-256.json
tfclip/configs/ViT-B-16-SigLIP-384.json
tfclip/configs/ViT-B-16-SigLIP-512.json
tfclip/configs/ViT-B-16-SigLIP-i18n-256.json
tfclip/configs/ViT-B-16-SigLIP.json
tfclip/configs/ViT-B-16-plus-240.json
tfclip/configs/ViT-B-16-quickgelu.json
tfclip/configs/ViT-B-16.json
tfclip/configs/ViT-B-32-256.json
tfclip/configs/ViT-B-32-Long-quickgelu.json
tfclip/configs/ViT-B-32-quickgelu.json
tfclip/configs/ViT-B-32.json
tfclip/configs/ViT-H-14-378-quickgelu.json
tfclip/configs/ViT-H-14-CLIPA-336.json
tfclip/configs/ViT-H-14-CLIPA.json
tfclip/configs/ViT-H-14-quickgelu.json
tfclip/configs/ViT-H-14.json
tfclip/configs/ViT-L-14-336-quickgelu.json
tfclip/configs/ViT-L-14-CLIPA-336.json
tfclip/configs/ViT-L-14-CLIPA.json
tfclip/configs/ViT-L-14-Long-336-quickgelu.json
tfclip/configs/ViT-L-14-Long-quickgelu.json
tfclip/configs/ViT-L-14-quickgelu.json
tfclip/configs/ViT-L-14.json
tfclip/configs/ViT-L-16-SigLIP-256.json
tfclip/configs/ViT-L-16-SigLIP-384.json
tfclip/configs/ViT-SO400M-14-SigLIP-378.json
tfclip/configs/ViT-SO400M-14-SigLIP.json
tfclip/configs/ViT-SO400M-16-SigLIP-i18n-256.json
tfclip/configs/ViT-bigG-14-CLIPA-336.json
tfclip/configs/ViT-bigG-14-CLIPA.json
tfclip/configs/ViT-bigG-14-quickgelu.json
